{
   "CodeGenerationMode": 3,
   "ContextClassName": "MusicLessonsDBContext",
   "ContextNamespace": null,
   "DefaultDacpacSchema": null,
   "FilterSchemas": false,
   "IncludeConnectionString": true,
   "ModelNamespace": null,
   "OutputContextPath": null,
   "OutputPath": "Models",
   "PreserveCasingWithRegex": true,
   "ProjectRootNamespace": "MusicLesson",
   "Schemas": null,
   "SelectedHandlebarsLanguage": 0,
   "SelectedToBeGenerated": 0,
   "Tables": [
      {
         "Name": "[dbo].[Duration]",
         "ObjectType": 0
      },
      {
         "Name": "[dbo].[Instrument]",
         "ObjectType": 0
      },
      {
         "Name": "[dbo].[Lessons]",
         "ObjectType": 0
      },
      {
         "Name": "[dbo].[Letters]",
         "ObjectType": 0
      },
      {
         "Name": "[dbo].[Students]",
         "ObjectType": 0
      },
      {
         "Name": "[dbo].[Tutors]",
         "ObjectType": 0
      }
   ],
   "UiHint": "DESKTOP-4504LM0.MusicLessonsDB",
   "UseBoolPropertiesWithoutDefaultSql": false,
   "UseDatabaseNames": true,
   "UseDbContextSplitting": false,
   "UseFluentApiOnly": false,
   "UseHandleBars": false,
   "UseHierarchyId": false,
   "UseInflector": false,
   "UseLegacyPluralizer": false,
   "UseManyToManyEntity": false,
   "UseNoConstructor": false,
   "UseNoDefaultConstructor": false,
   "UseNoNavigations": false,
   "UseNoObjectFilter": false,
   "UseNodaTime": false,
   "UseNullableReferences": false,
   "UseSchemaFolders": false,
   "UseSpatial": false,
   "UseT4": false
}